{
	"09:30": {
		"close": 7.24,
		"high": 7.24,
		"low": 7.24,
		"open": 7.24,
		"volume": 1450
	},
	"09:44": {
		"close": 7.21,
		"high": 7.21,
		"low": 7.21,
		"open": 7.21,
		"volume": 400
	},
	"09:45": {
		"close": 7.2,
		"high": 7.2,
		"low": 7.2,
		"open": 7.2,
		"volume": 400
	},
	"09:46": {
		"close": 7.23,
		"high": 7.23,
		"low": 7.23,
		"open": 7.23,
		"volume": 100
	},
	"09:47": {
		"close": 7.2,
		"high": 7.23,
		"low": 7.2,
		"open": 7.23,
		"volume": 200
	},
	"09:49": {
		"close": 7.2,
		"high": 7.2,
		"low": 7.2,
		"open": 7.2,
		"volume": 200
	},
	"09:51": {
		"close": 7.23,
		"high": 7.23,
		"low": 7.21,
		"open": 7.22,
		"volume": 300
	},
	"09:53": {
		"close": 7.21,
		"high": 7.21,
		"low": 7.21,
		"open": 7.21,
		"volume": 100
	},
	"10:00": {
		"close": 7.2,
		"high": 7.2,
		"low": 7.2,
		"open": 7.2,
		"volume": 200
	},
	"10:03": {
		"close": 7.2,
		"high": 7.2,
		"low": 7.2,
		"open": 7.2,
		"volume": 300
	},
	"10:05": {
		"close": 7.19,
		"high": 7.19,
		"low": 7.19,
		"open": 7.19,
		"volume": 100
	},
	"10:08": {
		"close": 7.19,
		"high": 7.19,
		"low": 7.19,
		"open": 7.19,
		"volume": 100
	},
	"10:09": {
		"close": 7.19,
		"high": 7.2,
		"low": 7.19,
		"open": 7.2,
		"volume": 200
	},
	"10:12": {
		"close": 7.2,
		"high": 7.2,
		"low": 7.2,
		"open": 7.2,
		"volume": 200
	},
	"10:13": {
		"close": 7.21,
		"high": 7.21,
		"low": 7.2,
		"open": 7.2,
		"volume": 400
	},
	"10:16": {
		"close": 7.215,
		"high": 7.215,
		"low": 7.215,
		"open": 7.215,
		"volume": 200
	},
	"10:18": {
		"close": 7.215,
		"high": 7.215,
		"low": 7.215,
		"open": 7.215,
		"volume": 400
	},
	"10:19": {
		"close": 7.215,
		"high": 7.215,
		"low": 7.215,
		"open": 7.215,
		"volume": 200
	},
	"10:21": {
		"close": 7.21,
		"high": 7.215,
		"low": 7.2,
		"open": 7.21,
		"volume": 1800
	},
	"10:22": {
		"close": 7.215,
		"high": 7.215,
		"low": 7.21,
		"open": 7.21,
		"volume": 900
	},
	"10:23": {
		"close": 7.215,
		"high": 7.215,
		"low": 7.215,
		"open": 7.215,
		"volume": 300
	},
	"10:26": {
		"close": 7.2,
		"high": 7.2,
		"low": 7.2,
		"open": 7.2,
		"volume": 400
	},
	"10:32": {
		"close": 7.2,
		"high": 7.2,
		"low": 7.2,
		"open": 7.2,
		"volume": 900
	},
	"10:33": {
		"close": 7.2,
		"high": 7.2,
		"low": 7.2,
		"open": 7.2,
		"volume": 100
	},
	"10:34": {
		"close": 7.19,
		"high": 7.19,
		"low": 7.18,
		"open": 7.18,
		"volume": 200
	},
	"10:35": {
		"close": 7.19,
		"high": 7.19,
		"low": 7.19,
		"open": 7.19,
		"volume": 100
	},
	"10:36": {
		"close": 7.16,
		"high": 7.19,
		"low": 7.16,
		"open": 7.19,
		"volume": 300
	},
	"10:37": {
		"close": 7.2,
		"high": 7.2,
		"low": 7.18,
		"open": 7.18,
		"volume": 600
	},
	"10:38": {
		"close": 7.2,
		"high": 7.2,
		"low": 7.2,
		"open": 7.2,
		"volume": 1900
	},
	"10:39": {
		"close": 7.18,
		"high": 7.2,
		"low": 7.18,
		"open": 7.2,
		"volume": 2800
	},
	"10:40": {
		"close": 7.19,
		"high": 7.19,
		"low": 7.18,
		"open": 7.18,
		"volume": 300
	},
	"10:41": {
		"close": 7.15,
		"high": 7.15,
		"low": 7.15,
		"open": 7.15,
		"volume": 300
	},
	"10:42": {
		"close": 7.15,
		"high": 7.16,
		"low": 7.15,
		"open": 7.15,
		"volume": 1200
	},
	"10:43": {
		"close": 7.15,
		"high": 7.17,
		"low": 7.15,
		"open": 7.16,
		"volume": 400
	},
	"10:44": {
		"close": 7.19,
		"high": 7.19,
		"low": 7.15,
		"open": 7.15,
		"volume": 200
	},
	"10:45": {
		"close": 7.15,
		"high": 7.15,
		"low": 7.15,
		"open": 7.15,
		"volume": 100
	},
	"10:46": {
		"close": 7.17,
		"high": 7.18,
		"low": 7.15,
		"open": 7.15,
		"volume": 1200
	},
	"10:47": {
		"close": 7.18,
		"high": 7.19,
		"low": 7.16,
		"open": 7.17,
		"volume": 1700
	},
	"10:50": {
		"close": 7.16,
		"high": 7.175,
		"low": 7.16,
		"open": 7.175,
		"volume": 200
	},
	"10:52": {
		"close": 7.18,
		"high": 7.18,
		"low": 7.17,
		"open": 7.17,
		"volume": 200
	},
	"10:53": {
		"close": 7.17,
		"high": 7.17,
		"low": 7.17,
		"open": 7.17,
		"volume": 300
	},
	"10:54": {
		"close": 7.17,
		"high": 7.17,
		"low": 7.17,
		"open": 7.17,
		"volume": 100
	},
	"10:55": {
		"close": 7.18,
		"high": 7.19,
		"low": 7.18,
		"open": 7.19,
		"volume": 600
	},
	"10:56": {
		"close": 7.18,
		"high": 7.2,
		"low": 7.18,
		"open": 7.18,
		"volume": 400
	},
	"10:58": {
		"close": 7.19,
		"high": 7.19,
		"low": 7.19,
		"open": 7.19,
		"volume": 200
	},
	"10:59": {
		"close": 7.21,
		"high": 7.21,
		"low": 7.18,
		"open": 7.19,
		"volume": 1000
	},
	"11:01": {
		"close": 7.17,
		"high": 7.18,
		"low": 7.17,
		"open": 7.17,
		"volume": 900
	},
	"11:06": {
		"close": 7.185,
		"high": 7.185,
		"low": 7.17,
		"open": 7.17,
		"volume": 300
	},
	"11:07": {
		"close": 7.17,
		"high": 7.17,
		"low": 7.17,
		"open": 7.17,
		"volume": 700
	},
	"11:08": {
		"close": 7.175,
		"high": 7.175,
		"low": 7.16,
		"open": 7.175,
		"volume": 400
	},
	"11:11": {
		"close": 7.175,
		"high": 7.18,
		"low": 7.175,
		"open": 7.18,
		"volume": 200
	},
	"11:13": {
		"close": 7.22,
		"high": 7.22,
		"low": 7.175,
		"open": 7.175,
		"volume": 1900
	},
	"11:15": {
		"close": 7.19,
		"high": 7.19,
		"low": 7.19,
		"open": 7.19,
		"volume": 300
	},
	"11:16": {
		"close": 7.17,
		"high": 7.18,
		"low": 7.17,
		"open": 7.18,
		"volume": 400
	},
	"11:17": {
		"close": 7.18,
		"high": 7.18,
		"low": 7.175,
		"open": 7.175,
		"volume": 25600
	},
	"11:19": {
		"close": 7.18,
		"high": 7.18,
		"low": 7.18,
		"open": 7.18,
		"volume": 700
	},
	"11:21": {
		"close": 7.18,
		"high": 7.18,
		"low": 7.18,
		"open": 7.18,
		"volume": 1400
	},
	"11:22": {
		"close": 7.18,
		"high": 7.18,
		"low": 7.18,
		"open": 7.18,
		"volume": 100
	},
	"11:24": {
		"close": 7.18,
		"high": 7.18,
		"low": 7.18,
		"open": 7.18,
		"volume": 900
	},
	"11:30": {
		"close": 7.21,
		"high": 7.21,
		"low": 7.18,
		"open": 7.185,
		"volume": 1203
	},
	"11:31": {
		"close": 7.2,
		"high": 7.24,
		"low": 7.2,
		"open": 7.2,
		"volume": 1900
	},
	"11:32": {
		"close": 7.18,
		"high": 7.195,
		"low": 7.17,
		"open": 7.19,
		"volume": 1200
	},
	"11:36": {
		"close": 7.19,
		"high": 7.19,
		"low": 7.19,
		"open": 7.19,
		"volume": 300
	},
	"11:37": {
		"close": 7.19,
		"high": 7.19,
		"low": 7.19,
		"open": 7.19,
		"volume": 300
	},
	"11:46": {
		"close": 7.17,
		"high": 7.17,
		"low": 7.17,
		"open": 7.17,
		"volume": 200
	},
	"11:48": {
		"close": 7.19,
		"high": 7.19,
		"low": 7.175,
		"open": 7.19,
		"volume": 400
	},
	"11:52": {
		"close": 7.19,
		"high": 7.195,
		"low": 7.19,
		"open": 7.195,
		"volume": 600
	},
	"11:54": {
		"close": 7.19,
		"high": 7.19,
		"low": 7.18,
		"open": 7.18,
		"volume": 200
	},
	"11:59": {
		"close": 7.18,
		"high": 7.18,
		"low": 7.18,
		"open": 7.18,
		"volume": 100
	},
	"12:00": {
		"close": 7.17,
		"high": 7.18,
		"low": 7.17,
		"open": 7.18,
		"volume": 600
	},
	"12:02": {
		"close": 7.17,
		"high": 7.17,
		"low": 7.17,
		"open": 7.17,
		"volume": 200
	},
	"12:07": {
		"close": 7.175,
		"high": 7.175,
		"low": 7.17,
		"open": 7.17,
		"volume": 400
	},
	"12:08": {
		"close": 7.16,
		"high": 7.17,
		"low": 7.16,
		"open": 7.16,
		"volume": 400
	},
	"12:09": {
		"close": 7.16,
		"high": 7.16,
		"low": 7.16,
		"open": 7.16,
		"volume": 100
	},
	"12:10": {
		"close": 7.16,
		"high": 7.16,
		"low": 7.16,
		"open": 7.16,
		"volume": 100
	},
	"12:20": {
		"close": 7.17,
		"high": 7.17,
		"low": 7.17,
		"open": 7.17,
		"volume": 100
	},
	"12:22": {
		"close": 7.17,
		"high": 7.17,
		"low": 7.17,
		"open": 7.17,
		"volume": 200
	},
	"12:23": {
		"close": 7.16,
		"high": 7.16,
		"low": 7.16,
		"open": 7.16,
		"volume": 100
	},
	"12:28": {
		"close": 7.17,
		"high": 7.1899,
		"low": 7.17,
		"open": 7.1899,
		"volume": 440
	},
	"12:29": {
		"close": 7.17,
		"high": 7.17,
		"low": 7.17,
		"open": 7.17,
		"volume": 100
	},
	"12:32": {
		"close": 7.17,
		"high": 7.17,
		"low": 7.17,
		"open": 7.17,
		"volume": 400
	},
	"12:37": {
		"close": 7.16,
		"high": 7.165,
		"low": 7.16,
		"open": 7.165,
		"volume": 500
	},
	"12:39": {
		"close": 7.16,
		"high": 7.16,
		"low": 7.15,
		"open": 7.16,
		"volume": 600
	},
	"12:40": {
		"close": 7.15,
		"high": 7.16,
		"low": 7.14,
		"open": 7.16,
		"volume": 800
	},
	"12:41": {
		"close": 7.13,
		"high": 7.13,
		"low": 7.13,
		"open": 7.13,
		"volume": 100
	},
	"12:42": {
		"close": 7.13,
		"high": 7.13,
		"low": 7.13,
		"open": 7.13,
		"volume": 100
	},
	"12:46": {
		"close": 7.15,
		"high": 7.15,
		"low": 7.15,
		"open": 7.15,
		"volume": 500
	},
	"12:48": {
		"close": 7.13,
		"high": 7.13,
		"low": 7.13,
		"open": 7.13,
		"volume": 100
	},
	"12:54": {
		"close": 7.13,
		"high": 7.13,
		"low": 7.13,
		"open": 7.13,
		"volume": 100
	},
	"12:58": {
		"close": 7.15,
		"high": 7.15,
		"low": 7.15,
		"open": 7.15,
		"volume": 100
	},
	"13:01": {
		"close": 7.15,
		"high": 7.15,
		"low": 7.15,
		"open": 7.15,
		"volume": 1100
	},
	"13:02": {
		"close": 7.15,
		"high": 7.15,
		"low": 7.15,
		"open": 7.15,
		"volume": 100
	},
	"13:03": {
		"close": 7.14,
		"high": 7.14,
		"low": 7.14,
		"open": 7.14,
		"volume": 300
	},
	"13:10": {
		"close": 7.14,
		"high": 7.14,
		"low": 7.14,
		"open": 7.14,
		"volume": 100
	},
	"13:11": {
		"close": 7.14,
		"high": 7.145,
		"low": 7.14,
		"open": 7.14,
		"volume": 400
	},
	"13:12": {
		"close": 7.135,
		"high": 7.135,
		"low": 7.135,
		"open": 7.135,
		"volume": 100
	},
	"13:22": {
		"close": 7.1,
		"high": 7.12,
		"low": 7.06,
		"open": 7.12,
		"volume": 4067
	},
	"13:23": {
		"close": 7.07,
		"high": 7.1,
		"low": 7.07,
		"open": 7.1,
		"volume": 990
	},
	"13:24": {
		"close": 7.07,
		"high": 7.07,
		"low": 7.07,
		"open": 7.07,
		"volume": 100
	},
	"13:25": {
		"close": 7.07,
		"high": 7.07,
		"low": 7.07,
		"open": 7.07,
		"volume": 200
	},
	"13:27": {
		"close": 7.09,
		"high": 7.09,
		"low": 7.09,
		"open": 7.09,
		"volume": 100
	},
	"13:29": {
		"close": 7.09,
		"high": 7.09,
		"low": 7.09,
		"open": 7.09,
		"volume": 100
	},
	"13:30": {
		"close": 7.1,
		"high": 7.1,
		"low": 7.1,
		"open": 7.1,
		"volume": 100
	},
	"13:39": {
		"close": 7.095,
		"high": 7.095,
		"low": 7.095,
		"open": 7.095,
		"volume": 100
	},
	"13:51": {
		"close": 7.11,
		"high": 7.11,
		"low": 7.11,
		"open": 7.11,
		"volume": 100
	},
	"13:56": {
		"close": 7.105,
		"high": 7.11,
		"low": 7.105,
		"open": 7.11,
		"volume": 600
	},
	"13:57": {
		"close": 7.105,
		"high": 7.105,
		"low": 7.105,
		"open": 7.105,
		"volume": 200
	},
	"13:58": {
		"close": 7.09,
		"high": 7.11,
		"low": 7.09,
		"open": 7.11,
		"volume": 300
	},
	"13:59": {
		"close": 7.09,
		"high": 7.09,
		"low": 7.09,
		"open": 7.09,
		"volume": 100
	},
	"14:02": {
		"close": 7.09,
		"high": 7.09,
		"low": 7.09,
		"open": 7.09,
		"volume": 100
	},
	"14:07": {
		"close": 7.125,
		"high": 7.125,
		"low": 7.11,
		"open": 7.12,
		"volume": 700
	},
	"14:08": {
		"close": 7.1115,
		"high": 7.1115,
		"low": 7.1115,
		"open": 7.1115,
		"volume": 100
	},
	"14:11": {
		"close": 7.11,
		"high": 7.11,
		"low": 7.11,
		"open": 7.11,
		"volume": 200
	},
	"14:13": {
		"close": 7.13,
		"high": 7.13,
		"low": 7.13,
		"open": 7.13,
		"volume": 100
	},
	"14:18": {
		"close": 7.12,
		"high": 7.12,
		"low": 7.12,
		"open": 7.12,
		"volume": 100
	},
	"14:19": {
		"close": 7.135,
		"high": 7.135,
		"low": 7.135,
		"open": 7.135,
		"volume": 100
	},
	"14:23": {
		"close": 7.135,
		"high": 7.135,
		"low": 7.135,
		"open": 7.135,
		"volume": 400
	},
	"14:24": {
		"close": 7.12,
		"high": 7.135,
		"low": 7.12,
		"open": 7.135,
		"volume": 300
	},
	"14:37": {
		"close": 7.135,
		"high": 7.135,
		"low": 7.135,
		"open": 7.135,
		"volume": 300
	},
	"14:39": {
		"close": 7.12,
		"high": 7.12,
		"low": 7.12,
		"open": 7.12,
		"volume": 200
	},
	"14:40": {
		"close": 7.04,
		"high": 7.1,
		"low": 7.04,
		"open": 7.09,
		"volume": 5550
	},
	"14:42": {
		"close": 7.06,
		"high": 7.06,
		"low": 7.04,
		"open": 7.04,
		"volume": 400
	},
	"14:43": {
		"close": 7.06,
		"high": 7.06,
		"low": 7.02,
		"open": 7.04,
		"volume": 991
	},
	"14:45": {
		"close": 7.03,
		"high": 7.05,
		"low": 7.03,
		"open": 7.05,
		"volume": 2100
	},
	"14:47": {
		"close": 7.03,
		"high": 7.03,
		"low": 7.03,
		"open": 7.03,
		"volume": 100
	},
	"14:48": {
		"close": 7.03,
		"high": 7.03,
		"low": 7.03,
		"open": 7.03,
		"volume": 100
	},
	"14:50": {
		"close": 7.06,
		"high": 7.06,
		"low": 7.04,
		"open": 7.04,
		"volume": 400
	},
	"14:52": {
		"close": 7.05,
		"high": 7.05,
		"low": 7.05,
		"open": 7.05,
		"volume": 100
	},
	"14:54": {
		"close": 7.07,
		"high": 7.07,
		"low": 7.07,
		"open": 7.07,
		"volume": 400
	},
	"14:55": {
		"close": 7.09,
		"high": 7.09,
		"low": 7.09,
		"open": 7.09,
		"volume": 100
	},
	"14:56": {
		"close": 7.09,
		"high": 7.09,
		"low": 7.09,
		"open": 7.09,
		"volume": 100
	},
	"14:58": {
		"close": 7.07,
		"high": 7.0925,
		"low": 7.07,
		"open": 7.07,
		"volume": 500
	},
	"14:59": {
		"close": 7.075,
		"high": 7.12,
		"low": 7.07,
		"open": 7.07,
		"volume": 300
	},
	"15:01": {
		"close": 7.07,
		"high": 7.07,
		"low": 7.07,
		"open": 7.07,
		"volume": 200
	},
	"15:03": {
		"close": 7.08,
		"high": 7.08,
		"low": 7.08,
		"open": 7.08,
		"volume": 500
	},
	"15:05": {
		"close": 7.07,
		"high": 7.12,
		"low": 7.07,
		"open": 7.12,
		"volume": 200
	},
	"15:07": {
		"close": 7.09,
		"high": 7.09,
		"low": 7.07,
		"open": 7.07,
		"volume": 600
	},
	"15:08": {
		"close": 7.07,
		"high": 7.07,
		"low": 7.07,
		"open": 7.07,
		"volume": 100
	},
	"15:10": {
		"close": 7.07,
		"high": 7.07,
		"low": 7.07,
		"open": 7.07,
		"volume": 100
	},
	"15:14": {
		"close": 7.07,
		"high": 7.07,
		"low": 7.07,
		"open": 7.07,
		"volume": 5300
	},
	"15:15": {
		"close": 6.99,
		"high": 7.07,
		"low": 6.99,
		"open": 7.07,
		"volume": 5133
	},
	"15:20": {
		"close": 6.99,
		"high": 6.99,
		"low": 6.98,
		"open": 6.99,
		"volume": 900
	},
	"15:22": {
		"close": 6.98,
		"high": 6.98,
		"low": 6.98,
		"open": 6.98,
		"volume": 100
	},
	"15:23": {
		"close": 6.99,
		"high": 6.99,
		"low": 6.99,
		"open": 6.99,
		"volume": 100
	},
	"15:25": {
		"close": 6.98,
		"high": 6.99,
		"low": 6.98,
		"open": 6.98,
		"volume": 1000
	},
	"15:26": {
		"close": 6.9945,
		"high": 7,
		"low": 6.98,
		"open": 6.98,
		"volume": 1700
	},
	"15:27": {
		"close": 7.02,
		"high": 7.02,
		"low": 6.99,
		"open": 6.99,
		"volume": 2200
	},
	"15:30": {
		"close": 7.02,
		"high": 7.02,
		"low": 7,
		"open": 7,
		"volume": 400
	},
	"15:31": {
		"close": 7.02,
		"high": 7.02,
		"low": 7,
		"open": 7.02,
		"volume": 1200
	},
	"15:32": {
		"close": 7.0145,
		"high": 7.0316,
		"low": 7.01,
		"open": 7.01,
		"volume": 4275
	},
	"15:33": {
		"close": 7.01,
		"high": 7.01,
		"low": 7.01,
		"open": 7.01,
		"volume": 100
	},
	"15:34": {
		"close": 7.01,
		"high": 7.027,
		"low": 7.01,
		"open": 7.01,
		"volume": 820
	},
	"15:35": {
		"close": 7,
		"high": 7.01,
		"low": 6.99,
		"open": 7,
		"volume": 1400
	},
	"15:36": {
		"close": 7,
		"high": 7,
		"low": 7,
		"open": 7,
		"volume": 100
	},
	"15:37": {
		"close": 7.005,
		"high": 7.005,
		"low": 7.005,
		"open": 7.005,
		"volume": 100
	},
	"15:39": {
		"close": 7.03,
		"high": 7.03,
		"low": 7.01,
		"open": 7.01,
		"volume": 600
	},
	"15:41": {
		"close": 7,
		"high": 7.03,
		"low": 7,
		"open": 7.03,
		"volume": 500
	},
	"15:43": {
		"close": 6.97,
		"high": 7.01,
		"low": 6.97,
		"open": 7.01,
		"volume": 2699
	},
	"15:44": {
		"close": 6.9975,
		"high": 6.9975,
		"low": 6.99,
		"open": 6.99,
		"volume": 400
	},
	"15:45": {
		"close": 7,
		"high": 7,
		"low": 6.995,
		"open": 7,
		"volume": 700
	},
	"15:46": {
		"close": 6.995,
		"high": 6.995,
		"low": 6.995,
		"open": 6.995,
		"volume": 100
	},
	"15:47": {
		"close": 7,
		"high": 7,
		"low": 7,
		"open": 7,
		"volume": 100
	},
	"15:48": {
		"close": 7,
		"high": 7,
		"low": 7,
		"open": 7,
		"volume": 100
	},
	"15:49": {
		"close": 7,
		"high": 7,
		"low": 7,
		"open": 7,
		"volume": 100
	},
	"15:50": {
		"close": 6.98,
		"high": 6.99,
		"low": 6.98,
		"open": 6.99,
		"volume": 300
	},
	"15:51": {
		"close": 6.99,
		"high": 6.99,
		"low": 6.99,
		"open": 6.99,
		"volume": 100
	},
	"15:52": {
		"close": 6.97,
		"high": 6.98,
		"low": 6.97,
		"open": 6.98,
		"volume": 314
	},
	"15:53": {
		"close": 6.98,
		"high": 6.98,
		"low": 6.98,
		"open": 6.98,
		"volume": 300
	},
	"15:54": {
		"close": 6.98,
		"high": 6.98,
		"low": 6.98,
		"open": 6.98,
		"volume": 100
	},
	"15:55": {
		"close": 6.98,
		"high": 6.99,
		"low": 6.97,
		"open": 6.99,
		"volume": 1459
	},
	"15:56": {
		"close": 6.99,
		"high": 6.99,
		"low": 6.99,
		"open": 6.99,
		"volume": 100
	},
	"15:57": {
		"close": 6.99,
		"high": 6.99,
		"low": 6.99,
		"open": 6.99,
		"volume": 100
	},
	"15:58": {
		"close": 6.995,
		"high": 6.995,
		"low": 6.995,
		"open": 6.995,
		"volume": 100
	},
	"15:59": {
		"close": 6.9999,
		"high": 6.9999,
		"low": 6.9999,
		"open": 6.9999,
		"volume": 3000
	},
	"16:00": {
		"close": 6.99,
		"high": 6.995,
		"low": 6.99,
		"open": 6.995,
		"volume": 300
	}
}