{
	"09:32": {
		"close": 2.2,
		"high": 2.2,
		"low": 2.2,
		"open": 2.2,
		"volume": 8505
	},
	"09:36": {
		"close": 2.14,
		"high": 2.16,
		"low": 2.14,
		"open": 2.16,
		"volume": 500
	},
	"09:40": {
		"close": 2.11,
		"high": 2.11,
		"low": 2.11,
		"open": 2.11,
		"volume": 100
	},
	"09:45": {
		"close": 2.12,
		"high": 2.12,
		"low": 2.12,
		"open": 2.12,
		"volume": 100
	},
	"09:48": {
		"close": 2.12,
		"high": 2.12,
		"low": 2.12,
		"open": 2.12,
		"volume": 100
	},
	"09:50": {
		"close": 2.13,
		"high": 2.13,
		"low": 2.13,
		"open": 2.13,
		"volume": 100
	},
	"09:53": {
		"close": 2.14,
		"high": 2.14,
		"low": 2.14,
		"open": 2.14,
		"volume": 100
	},
	"09:55": {
		"close": 2.14,
		"high": 2.14,
		"low": 2.14,
		"open": 2.14,
		"volume": 200
	},
	"09:58": {
		"close": 2.15,
		"high": 2.15,
		"low": 2.15,
		"open": 2.15,
		"volume": 100
	},
	"10:00": {
		"close": 2.15,
		"high": 2.15,
		"low": 2.15,
		"open": 2.15,
		"volume": 3089
	},
	"10:01": {
		"close": 2.14,
		"high": 2.14,
		"low": 2.14,
		"open": 2.14,
		"volume": 100
	},
	"10:03": {
		"close": 2.14,
		"high": 2.15,
		"low": 2.14,
		"open": 2.1466,
		"volume": 4600
	},
	"10:04": {
		"close": 2.1466,
		"high": 2.1466,
		"low": 2.1466,
		"open": 2.1466,
		"volume": 1000
	},
	"10:06": {
		"close": 2.15,
		"high": 2.15,
		"low": 2.15,
		"open": 2.15,
		"volume": 300
	},
	"10:07": {
		"close": 2.15,
		"high": 2.15,
		"low": 2.14,
		"open": 2.14,
		"volume": 1500
	},
	"10:16": {
		"close": 2.14,
		"high": 2.14,
		"low": 2.14,
		"open": 2.14,
		"volume": 100
	},
	"10:18": {
		"close": 2.15,
		"high": 2.15,
		"low": 2.15,
		"open": 2.15,
		"volume": 100
	},
	"10:19": {
		"close": 2.15,
		"high": 2.15,
		"low": 2.15,
		"open": 2.15,
		"volume": 100
	},
	"10:21": {
		"close": 2.15,
		"high": 2.15,
		"low": 2.15,
		"open": 2.15,
		"volume": 200
	},
	"10:23": {
		"close": 2.15,
		"high": 2.15,
		"low": 2.15,
		"open": 2.15,
		"volume": 200
	},
	"10:25": {
		"close": 2.15,
		"high": 2.15,
		"low": 2.15,
		"open": 2.15,
		"volume": 100
	},
	"10:26": {
		"close": 2.15,
		"high": 2.1626,
		"low": 2.15,
		"open": 2.1626,
		"volume": 850
	},
	"10:27": {
		"close": 2.15,
		"high": 2.15,
		"low": 2.15,
		"open": 2.15,
		"volume": 100
	},
	"10:29": {
		"close": 2.15,
		"high": 2.15,
		"low": 2.15,
		"open": 2.15,
		"volume": 200
	},
	"10:31": {
		"close": 2.15,
		"high": 2.15,
		"low": 2.15,
		"open": 2.15,
		"volume": 100
	},
	"10:33": {
		"close": 2.15,
		"high": 2.15,
		"low": 2.15,
		"open": 2.15,
		"volume": 100
	},
	"10:34": {
		"close": 2.15,
		"high": 2.15,
		"low": 2.15,
		"open": 2.15,
		"volume": 100
	},
	"10:35": {
		"close": 2.15,
		"high": 2.15,
		"low": 2.15,
		"open": 2.15,
		"volume": 100
	},
	"10:36": {
		"close": 2.15,
		"high": 2.15,
		"low": 2.15,
		"open": 2.15,
		"volume": 100
	},
	"10:37": {
		"close": 2.15,
		"high": 2.15,
		"low": 2.15,
		"open": 2.15,
		"volume": 100
	},
	"10:39": {
		"close": 2.15,
		"high": 2.15,
		"low": 2.15,
		"open": 2.15,
		"volume": 200
	},
	"10:41": {
		"close": 2.15,
		"high": 2.15,
		"low": 2.15,
		"open": 2.15,
		"volume": 200
	},
	"10:43": {
		"close": 2.15,
		"high": 2.15,
		"low": 2.15,
		"open": 2.15,
		"volume": 100
	},
	"10:44": {
		"close": 2.15,
		"high": 2.15,
		"low": 2.15,
		"open": 2.15,
		"volume": 100
	},
	"10:45": {
		"close": 2.15,
		"high": 2.15,
		"low": 2.15,
		"open": 2.15,
		"volume": 100
	},
	"10:46": {
		"close": 2.15,
		"high": 2.15,
		"low": 2.15,
		"open": 2.15,
		"volume": 100
	},
	"10:47": {
		"close": 2.15,
		"high": 2.15,
		"low": 2.15,
		"open": 2.15,
		"volume": 100
	},
	"10:49": {
		"close": 2.15,
		"high": 2.15,
		"low": 2.15,
		"open": 2.15,
		"volume": 100
	},
	"10:50": {
		"close": 2.1476,
		"high": 2.1476,
		"low": 2.1476,
		"open": 2.1476,
		"volume": 5000
	},
	"10:51": {
		"close": 2.15,
		"high": 2.15,
		"low": 2.15,
		"open": 2.15,
		"volume": 100
	},
	"10:53": {
		"close": 2.15,
		"high": 2.15,
		"low": 2.15,
		"open": 2.15,
		"volume": 100
	},
	"10:54": {
		"close": 2.15,
		"high": 2.15,
		"low": 2.15,
		"open": 2.15,
		"volume": 100
	},
	"10:55": {
		"close": 2.15,
		"high": 2.15,
		"low": 2.15,
		"open": 2.15,
		"volume": 100
	},
	"10:57": {
		"close": 2.15,
		"high": 2.15,
		"low": 2.15,
		"open": 2.15,
		"volume": 200
	},
	"10:59": {
		"close": 2.15,
		"high": 2.15,
		"low": 2.15,
		"open": 2.15,
		"volume": 200
	},
	"11:02": {
		"close": 2.14,
		"high": 2.14,
		"low": 2.14,
		"open": 2.14,
		"volume": 100
	},
	"11:04": {
		"close": 2.14,
		"high": 2.14,
		"low": 2.14,
		"open": 2.14,
		"volume": 100
	},
	"11:07": {
		"close": 2.14,
		"high": 2.14,
		"low": 2.14,
		"open": 2.14,
		"volume": 100
	},
	"11:14": {
		"close": 2.1655,
		"high": 2.1655,
		"low": 2.155,
		"open": 2.155,
		"volume": 2000
	},
	"11:17": {
		"close": 2.15,
		"high": 2.16,
		"low": 2.15,
		"open": 2.15,
		"volume": 500
	},
	"11:24": {
		"close": 2.15,
		"high": 2.15,
		"low": 2.15,
		"open": 2.15,
		"volume": 100
	},
	"11:26": {
		"close": 2.15,
		"high": 2.15,
		"low": 2.15,
		"open": 2.15,
		"volume": 100
	},
	"11:28": {
		"close": 2.15,
		"high": 2.15,
		"low": 2.15,
		"open": 2.15,
		"volume": 100
	},
	"11:30": {
		"close": 2.15,
		"high": 2.15,
		"low": 2.15,
		"open": 2.15,
		"volume": 100
	},
	"11:32": {
		"close": 2.15,
		"high": 2.15,
		"low": 2.15,
		"open": 2.15,
		"volume": 100
	},
	"11:34": {
		"close": 2.15,
		"high": 2.15,
		"low": 2.15,
		"open": 2.15,
		"volume": 100
	},
	"11:36": {
		"close": 2.15,
		"high": 2.15,
		"low": 2.15,
		"open": 2.15,
		"volume": 100
	},
	"11:37": {
		"close": 2.15,
		"high": 2.15,
		"low": 2.15,
		"open": 2.15,
		"volume": 4000
	},
	"11:38": {
		"close": 2.15,
		"high": 2.15,
		"low": 2.15,
		"open": 2.15,
		"volume": 100
	},
	"11:40": {
		"close": 2.15,
		"high": 2.15,
		"low": 2.15,
		"open": 2.15,
		"volume": 100
	},
	"11:42": {
		"close": 2.15,
		"high": 2.15,
		"low": 2.15,
		"open": 2.15,
		"volume": 100
	},
	"11:44": {
		"close": 2.15,
		"high": 2.15,
		"low": 2.15,
		"open": 2.15,
		"volume": 100
	},
	"11:46": {
		"close": 2.15,
		"high": 2.15,
		"low": 2.15,
		"open": 2.15,
		"volume": 100
	},
	"11:48": {
		"close": 2.15,
		"high": 2.15,
		"low": 2.15,
		"open": 2.15,
		"volume": 100
	},
	"11:50": {
		"close": 2.15,
		"high": 2.15,
		"low": 2.15,
		"open": 2.15,
		"volume": 100
	},
	"11:52": {
		"close": 2.15,
		"high": 2.15,
		"low": 2.15,
		"open": 2.15,
		"volume": 100
	},
	"11:54": {
		"close": 2.15,
		"high": 2.1538,
		"low": 2.15,
		"open": 2.15,
		"volume": 6540
	},
	"11:56": {
		"close": 2.15,
		"high": 2.15,
		"low": 2.15,
		"open": 2.15,
		"volume": 100
	},
	"11:58": {
		"close": 2.15,
		"high": 2.15,
		"low": 2.15,
		"open": 2.15,
		"volume": 100
	},
	"11:59": {
		"close": 2.1699,
		"high": 2.1699,
		"low": 2.1699,
		"open": 2.1699,
		"volume": 100
	},
	"12:00": {
		"close": 2.15,
		"high": 2.15,
		"low": 2.15,
		"open": 2.15,
		"volume": 100
	},
	"12:02": {
		"close": 2.15,
		"high": 2.15,
		"low": 2.15,
		"open": 2.15,
		"volume": 100
	},
	"12:04": {
		"close": 2.15,
		"high": 2.15,
		"low": 2.15,
		"open": 2.15,
		"volume": 100
	},
	"12:06": {
		"close": 2.15,
		"high": 2.15,
		"low": 2.15,
		"open": 2.15,
		"volume": 100
	},
	"12:07": {
		"close": 2.17,
		"high": 2.17,
		"low": 2.17,
		"open": 2.17,
		"volume": 200
	},
	"12:08": {
		"close": 2.15,
		"high": 2.15,
		"low": 2.15,
		"open": 2.15,
		"volume": 100
	},
	"12:10": {
		"close": 2.15,
		"high": 2.15,
		"low": 2.15,
		"open": 2.15,
		"volume": 100
	},
	"12:11": {
		"close": 2.16,
		"high": 2.16,
		"low": 2.15,
		"open": 2.15,
		"volume": 7100
	},
	"12:12": {
		"close": 2.16,
		"high": 2.16,
		"low": 2.16,
		"open": 2.16,
		"volume": 2600
	},
	"12:13": {
		"close": 2.16,
		"high": 2.16,
		"low": 2.16,
		"open": 2.16,
		"volume": 3200
	},
	"12:17": {
		"close": 2.16,
		"high": 2.16,
		"low": 2.16,
		"open": 2.16,
		"volume": 1137
	},
	"12:30": {
		"close": 2.16,
		"high": 2.16,
		"low": 2.16,
		"open": 2.16,
		"volume": 400
	},
	"12:37": {
		"close": 2.18,
		"high": 2.18,
		"low": 2.17,
		"open": 2.17,
		"volume": 300
	},
	"12:38": {
		"close": 2.1601,
		"high": 2.1601,
		"low": 2.1601,
		"open": 2.1601,
		"volume": 1000
	},
	"12:40": {
		"close": 2.162,
		"high": 2.162,
		"low": 2.162,
		"open": 2.162,
		"volume": 600
	},
	"12:56": {
		"close": 2.16,
		"high": 2.168,
		"low": 2.16,
		"open": 2.168,
		"volume": 6500
	},
	"12:59": {
		"close": 2.19,
		"high": 2.19,
		"low": 2.19,
		"open": 2.19,
		"volume": 100
	},
	"13:02": {
		"close": 2.1878,
		"high": 2.1878,
		"low": 2.1878,
		"open": 2.1878,
		"volume": 2325
	},
	"13:04": {
		"close": 2.17,
		"high": 2.17,
		"low": 2.17,
		"open": 2.17,
		"volume": 4500
	},
	"13:07": {
		"close": 2.1825,
		"high": 2.185,
		"low": 2.18,
		"open": 2.18,
		"volume": 1818
	},
	"13:12": {
		"close": 2.17,
		"high": 2.17,
		"low": 2.17,
		"open": 2.17,
		"volume": 3500
	},
	"13:13": {
		"close": 2.17,
		"high": 2.17,
		"low": 2.17,
		"open": 2.17,
		"volume": 1000
	},
	"13:28": {
		"close": 2.17,
		"high": 2.17,
		"low": 2.17,
		"open": 2.17,
		"volume": 300
	},
	"13:37": {
		"close": 2.15,
		"high": 2.15,
		"low": 2.15,
		"open": 2.15,
		"volume": 600
	},
	"13:40": {
		"close": 2.15,
		"high": 2.15,
		"low": 2.15,
		"open": 2.15,
		"volume": 700
	},
	"13:45": {
		"close": 2.17,
		"high": 2.17,
		"low": 2.17,
		"open": 2.17,
		"volume": 100
	},
	"13:47": {
		"close": 2.1586,
		"high": 2.1586,
		"low": 2.1586,
		"open": 2.1586,
		"volume": 1000
	},
	"13:54": {
		"close": 2.1632,
		"high": 2.1632,
		"low": 2.1632,
		"open": 2.1632,
		"volume": 1000
	},
	"13:59": {
		"close": 2.16,
		"high": 2.16,
		"low": 2.16,
		"open": 2.16,
		"volume": 100
	},
	"14:04": {
		"close": 2.16,
		"high": 2.16,
		"low": 2.16,
		"open": 2.16,
		"volume": 100
	},
	"14:16": {
		"close": 2.15,
		"high": 2.15,
		"low": 2.15,
		"open": 2.15,
		"volume": 600
	},
	"14:24": {
		"close": 2.16,
		"high": 2.16,
		"low": 2.16,
		"open": 2.16,
		"volume": 500
	},
	"14:28": {
		"close": 2.1534,
		"high": 2.1534,
		"low": 2.1534,
		"open": 2.1534,
		"volume": 200
	},
	"14:30": {
		"close": 2.15,
		"high": 2.15,
		"low": 2.15,
		"open": 2.15,
		"volume": 100
	},
	"14:32": {
		"close": 2.1562,
		"high": 2.1562,
		"low": 2.1562,
		"open": 2.1562,
		"volume": 100
	},
	"14:34": {
		"close": 2.1501,
		"high": 2.1501,
		"low": 2.1501,
		"open": 2.1501,
		"volume": 221
	},
	"14:36": {
		"close": 2.16,
		"high": 2.16,
		"low": 2.1599,
		"open": 2.16,
		"volume": 600
	},
	"14:37": {
		"close": 2.16,
		"high": 2.16,
		"low": 2.1587,
		"open": 2.16,
		"volume": 1500
	},
	"14:38": {
		"close": 2.16,
		"high": 2.16,
		"low": 2.16,
		"open": 2.16,
		"volume": 2400
	},
	"14:48": {
		"close": 2.16,
		"high": 2.16,
		"low": 2.16,
		"open": 2.16,
		"volume": 800
	},
	"14:49": {
		"close": 2.15,
		"high": 2.15,
		"low": 2.15,
		"open": 2.15,
		"volume": 100
	},
	"14:50": {
		"close": 2.15,
		"high": 2.15,
		"low": 2.15,
		"open": 2.15,
		"volume": 100
	},
	"14:51": {
		"close": 2.16,
		"high": 2.16,
		"low": 2.1599,
		"open": 2.1599,
		"volume": 350
	},
	"14:52": {
		"close": 2.16,
		"high": 2.16,
		"low": 2.16,
		"open": 2.16,
		"volume": 1200
	},
	"14:53": {
		"close": 2.1566,
		"high": 2.16,
		"low": 2.1566,
		"open": 2.16,
		"volume": 200
	},
	"14:55": {
		"close": 2.16,
		"high": 2.16,
		"low": 2.16,
		"open": 2.16,
		"volume": 500
	},
	"14:59": {
		"close": 2.15,
		"high": 2.1699,
		"low": 2.15,
		"open": 2.1699,
		"volume": 4600
	},
	"15:02": {
		"close": 2.16,
		"high": 2.16,
		"low": 2.1599,
		"open": 2.1599,
		"volume": 1100
	},
	"15:03": {
		"close": 2.1599,
		"high": 2.1599,
		"low": 2.1599,
		"open": 2.1599,
		"volume": 1000
	},
	"15:04": {
		"close": 2.1599,
		"high": 2.1599,
		"low": 2.1599,
		"open": 2.1599,
		"volume": 1000
	},
	"15:06": {
		"close": 2.16,
		"high": 2.16,
		"low": 2.159,
		"open": 2.16,
		"volume": 2515
	},
	"15:08": {
		"close": 2.1584,
		"high": 2.1584,
		"low": 2.1584,
		"open": 2.1584,
		"volume": 100
	},
	"15:10": {
		"close": 2.1584,
		"high": 2.1584,
		"low": 2.1584,
		"open": 2.1584,
		"volume": 100
	},
	"15:11": {
		"close": 2.1584,
		"high": 2.1584,
		"low": 2.1584,
		"open": 2.1584,
		"volume": 100
	},
	"15:15": {
		"close": 2.16,
		"high": 2.16,
		"low": 2.16,
		"open": 2.16,
		"volume": 100
	},
	"15:21": {
		"close": 2.16,
		"high": 2.16,
		"low": 2.16,
		"open": 2.16,
		"volume": 100
	},
	"15:22": {
		"close": 2.1599,
		"high": 2.16,
		"low": 2.157,
		"open": 2.16,
		"volume": 5843
	},
	"15:23": {
		"close": 2.16,
		"high": 2.16,
		"low": 2.16,
		"open": 2.16,
		"volume": 200
	},
	"15:25": {
		"close": 2.16,
		"high": 2.16,
		"low": 2.16,
		"open": 2.16,
		"volume": 200
	},
	"15:29": {
		"close": 2.16,
		"high": 2.16,
		"low": 2.16,
		"open": 2.16,
		"volume": 200
	},
	"15:31": {
		"close": 2.15,
		"high": 2.16,
		"low": 2.15,
		"open": 2.16,
		"volume": 4685
	},
	"15:32": {
		"close": 2.14,
		"high": 2.16,
		"low": 2.14,
		"open": 2.15,
		"volume": 1410
	},
	"15:34": {
		"close": 2.143,
		"high": 2.143,
		"low": 2.143,
		"open": 2.143,
		"volume": 800
	},
	"15:35": {
		"close": 2.1652,
		"high": 2.1652,
		"low": 2.1652,
		"open": 2.1652,
		"volume": 100
	},
	"15:37": {
		"close": 2.15,
		"high": 2.15,
		"low": 2.15,
		"open": 2.15,
		"volume": 500
	},
	"15:38": {
		"close": 2.15,
		"high": 2.15,
		"low": 2.15,
		"open": 2.15,
		"volume": 5700
	},
	"15:40": {
		"close": 2.15,
		"high": 2.15,
		"low": 2.15,
		"open": 2.15,
		"volume": 100
	},
	"15:43": {
		"close": 2.15,
		"high": 2.15,
		"low": 2.15,
		"open": 2.15,
		"volume": 2630
	},
	"15:48": {
		"close": 2.15,
		"high": 2.15,
		"low": 2.15,
		"open": 2.15,
		"volume": 200
	},
	"15:51": {
		"close": 2.15,
		"high": 2.15,
		"low": 2.14,
		"open": 2.15,
		"volume": 1324
	},
	"15:52": {
		"close": 2.1484,
		"high": 2.15,
		"low": 2.1484,
		"open": 2.15,
		"volume": 400
	},
	"15:53": {
		"close": 2.15,
		"high": 2.15,
		"low": 2.15,
		"open": 2.15,
		"volume": 300
	},
	"15:54": {
		"close": 2.1484,
		"high": 2.1484,
		"low": 2.1484,
		"open": 2.1484,
		"volume": 100
	},
	"15:55": {
		"close": 2.15,
		"high": 2.15,
		"low": 2.14,
		"open": 2.14,
		"volume": 2035
	},
	"15:56": {
		"close": 2.16,
		"high": 2.17,
		"low": 2.16,
		"open": 2.1684,
		"volume": 500
	},
	"15:58": {
		"close": 2.1752,
		"high": 2.1752,
		"low": 2.16,
		"open": 2.16,
		"volume": 200
	},
	"15:59": {
		"close": 2.16,
		"high": 2.16,
		"low": 2.15,
		"open": 2.15,
		"volume": 400
	},
	"16:00": {
		"close": 2.15,
		"high": 2.155,
		"low": 2.15,
		"open": 2.155,
		"volume": 2900
	}
}